ipyquery/__init__.py
ipyquery/linq.py
ipyquery-0.0.6.dist-info/LICENSE
ipyquery-0.0.6.dist-info/METADATA
ipyquery-0.0.6.dist-info/WHEEL
ipyquery-0.0.6.dist-info/top_level.txt
ipyquery-0.0.6.dist-info/RECORD
