Metadata-Version: 2.1
Name: ipyquery
Version: 0.0.6
Summary: Linq for python
Home-page: https://github.com/immmdreza/ipyquery
Author: immmdreza
Author-email: ir310022@gmail.com
License: UNKNOWN
Project-URL: Bug Tracker, https://github.com/immmdreza/ipyquery/issues
Platform: UNKNOWN
Classifier: Programming Language :: Python :: 3
Classifier: License :: OSI Approved :: MIT License
Classifier: Operating System :: OS Independent
Requires-Python: >=3.6
License-File: LICENSE
